agentmon/__init__.py
agentmon-0.0.1.dist-info/METADATA
agentmon-0.0.1.dist-info/WHEEL
agentmon-0.0.1.dist-info/top_level.txt
agentmon-0.0.1.dist-info/RECORD
